stockcalc/__init__.py
stockcalc/__main__.py
stockcalc/core.py
stockcalc/_interface/__init__.py
stockcalc/_interface/input.py
stockcalc/_interface/output.py
stockcalc/api/__init__.py
stockcalc/api/alpha.py
stockcalc/exception/ApiGenericException.py
stockcalc/exception/InvalidApiCallException.py
stockcalc/exception/InvalidApiKeyException.py
stockcalc/exception/PercentileException.py
stockcalc/exception/TooManyRequestsException.py
stockcalc/exception/__init__.py
stockcacl-0.1.1.dist-info/LICENSE
stockcacl-0.1.1.dist-info/METADATA
stockcacl-0.1.1.dist-info/WHEEL
stockcacl-0.1.1.dist-info/top_level.txt
stockcacl-0.1.1.dist-info/RECORD
