Metadata-Version: 2.1
Name: stockcacl
Version: 0.1.1
Summary: Stock Calculator - Percentile Analysis
Home-page: https://github.com/antonioeatgoat/stockcacl/
Author: Antonio Mangiacapra
License: UNKNOWN
Platform: UNKNOWN
Classifier: Programming Language :: Python :: 3
Classifier: License :: OSI Approved :: MIT License
Classifier: Operating System :: OS Independent
Requires-Python: >=3.6
Requires-Dist: python-dotenv
Requires-Dist: pandas
Requires-Dist: requests
